{
  "meta": {
    "generated_at": "2026-05-12T14:37:37.056618+00:00",
    "market_status": "open",
    "pipeline_version": "3.1",
    "analysis_type": "short",
    "total_tickers": 15,
    "run_mode": "full",
    "tickers_updated": [
      "ASML",
      "PLTR",
      "MELI",
      "URNM",
      "FCX",
      "ISRG",
      "PWR",
      "XYL",
      "STNG",
      "SMH",
      "LNG",
      "SOXX",
      "QQQ",
      "SPY",
      "MU"
    ]
  },
  "stocks": [
    {
      "ticker": "SOXX",
      "company_name": "iShares Semiconductor ETF",
      "sector": "לא ידוע",
      "signal": "תיקון סקטוריאלי",
      "direction": "bearish",
      "confidence": 85,
      "earnings_insight": "קרן סל אינה מדווחת דוחות רווח רבעוניים. ביצועיה מושפעים מדוחות החברות המרכיבות אותה, בעיקר המובילות בסקטור המוליכים למחצה.",
      "bottom_line": "אזור איסוף: 508-510 דולר | יעד נזילות ראשון: 518-520 דולר | נקודת ביטול תזה: 505 דולר | יחס סיכוי/סיכון: 1.8:1",
      "catalysts": [
        {
          "type": "sector",
          "title": "דוחות רווח של חברות מוליכים למחצה מובילות",
          "description": "דוחות רווח עתידיים של ענקיות כמו NVIDIA, Broadcom או AMD, במיוחד בכל הנוגע לתחזיות שלהן, יכולים להשפיע באופן דרמטי על סנטימנט הסקטור ועל תנועת SOXX.",
          "impact": "לא ברור",
          "timeframe": "שבועות"
        },
        {
          "type": "macro",
          "title": "נתוני אינפלציה וריבית בארה\"ב",
          "description": "המשך עלייה באינפלציה או רמזים לבנק המרכזי בארה\"ב (פד) כי הריביות יישארו גבוהות יותר ולזמן ארוך יותר, עלולים לפגוע בסקטור הצמיחה כמו מוליכים למחצה.",
          "impact": "שלילי",
          "timeframe": "ימים/שבועות"
        },
        {
          "type": "technical",
          "title": "שבירת תמיכה ב-510 דולר",
          "description": "SOXX נסחרת כעת סביב 512 דולר, קרוב לרמת תמיכה קריטית. שבירה מתחת ל-510 דולר, במיוחד עם מחזור מסחר גבוה, עלולה להוביל לגל מכירות נוסף ולחיסול פוזיציות לונג.",
          "impact": "שלילי",
          "timeframe": "מיידי/ימים"
        }
      ],
      "questions": [
        {
          "question": "בהתחשב בכך ש-SOXX ירדה ב-3.82% היום, ובהינתן ש-10 המניות הגדולות מהוות מעל 60% ממשקל הקרן, כיצד תנועות חדות במניות כמו NVIDIA או Broadcom ישפיעו על הקרן בטווח הקצר?",
          "answer": "ריכוזיות גבוהה פירושה שהקרן מושפעת באופן דרמטי מביצועי מספר מצומצם של מניות. ירידה חדה במניות אלו, כפי שקורה לעיתים קרובות ביום של תיקון סקטוריאלי, תגרור את הקרן מטה באופן משמעותי.",
          "implication": "שלילי"
        },
        {
          "question": "האם דמי הניהול של SOXX (0.35%) נחשבים אטרקטיביים בהשוואה לקרנות סל אחרות בסקטור המוליכים למחצה, והאם הנזילות היומית הגבוהה מספיקה למנוע סליפג' משמעותי במקרה של יציאת כספים מהירה?",
          "answer": "דמי ניהול של 0.35% הם סבירים אך לא הנמוכים ביותר. הנזילות הגבוהה של SOXX (מיליוני מניות ביום) מבטיחה בדרך כלל שניתן להיכנס ולצאת מפוזיציות גדולות ללא סליפג' משמעותי, גם בימי פאניקה.",
          "implication": "ניטרלי"
        },
        {
          "question": "האם איכות ה\"זנב\" של החברות הקטנות יותר ב-SOXX, שאינן נמנות עם ענקיות השבבים, עלולה להוות גורם סיכון במקרה של האטה כלכלית רחבה או ירידה בביקוש למוצרי קצה?",
          "answer": "למרות ש-SOXX מורכבת בעיקר מחברות איכותיות, חלק מהחברות הקטנות יותר עשויות להיות פגיעות יותר להאטה כלכלית. עם זאת, המשקל הנמוך שלהן מפחית את ההשפעה הכוללת על הקרן בהשוואה למניות הליבה.",
          "implication": "ניטרלי"
        }
      ],
      "buzz_alert": "הבאז סביב סקטור המוליכים למחצה ממשיך להיות גבוה בשל ההתלהבות מ-AI, אך ישנה גם דאגה מהערכות שווי גבוהות ומתיקון אפשרי בשוק. הירידה של היום עשויה להגביר את החששות ממימוש רווחים. חלק מהרעש מגיע מגופי חדשות כלכליים ומאנליסטים המגיבים לנתוני מאקרו או לחדשות ספציפיות של חברות, אך סוחרים קצרי טווח מנצלים כל תנועה חדה. ההשפעה הכוללת היא של זהירות מוגברת.",
      "sources": [
        "https://finance.yahoo.com/quote/SOXX/",
        "https://www.ishares.com/us/products/239706/ishares-phlx-semiconductor-etf",
        "https://seekingalpha.com/symbol/SOXX",
        "https://finviz.com/quote.ashx?t=SOXX",
        "https://www.etf.com/SOXX"
      ],
      "analysis_type": "short",
      "market": "US",
      "price": 512.43,
      "change_pct": -3.82,
      "analyst_ratings": {
        "strongBuy": 0,
        "buy": 0,
        "hold": 0,
        "sell": 0,
        "strongSell": 0
      }
    },
    {
      "ticker": "QQQ",
      "company_name": "Invesco QQQ Trust",
      "sector": "לא ידוע",
      "signal": "תיקון קל בטכנולוגיה",
      "direction": "bearish",
      "confidence": 80,
      "earnings_insight": "קרן סל אינה מדווחת דוחות רווח רבעוניים. ביצועיה מושפעים מדוחות החברות המרכיבות אותה, בעיקר 100 החברות הגדולות בנאסד\"ק, עם דגש על ענקיות הטכנולוגיה.",
      "bottom_line": "אזור איסוף: 700-702 דולר | יעד נזילות ראשון: 708-710 דולר | נקודת ביטול תזה: 697.5 דולר | יחס סיכוי/סיכון: 1.6:1",
      "catalysts": [
        {
          "type": "macro",
          "title": "החלטות ריבית של הפד",
          "description": "כל רמז מצד הפד על שינוי במדיניות הריבית, במיוחד דחייה נוספת של הורדות ריבית, עלול להשפיע לרעה על סקטור הצמיחה והטכנולוגיה ש-QQQ מייצגת.",
          "impact": "שלילי",
          "timeframe": "שבועות"
        },
        {
          "type": "earnings",
          "title": "דוחות רווח של חברות טכנולוגיה מובילות",
          "description": "דוחות רווח חזקים או חלשים של ענקיות טכנולוגיה כמו Apple, Microsoft או Amazon יכולים להשפיע באופן משמעותי על תנועת QQQ, בהתחשב במשקלן הגבוה במדד.",
          "impact": "לא ברור",
          "timeframe": "שבועות"
        },
        {
          "type": "technical",
          "title": "שבירת קו מגמה עולה",
          "description": "QQQ נסחרת קרוב לשיא של 52 שבועות. ירידה מתחת לקו מגמה עולה שהתפתח לאחרונה, או מתחת לרמת תמיכה קריטית סביב 700 דולר, עלולה להפעיל לחץ מכירה נוסף.",
          "impact": "שלילי",
          "timeframe": "מיידי/ימים"
        }
      ],
      "questions": [
        {
          "question": "בהתחשב בירידה של 1.26% ב-QQQ היום, ובידיעה ש-5 המניות המובילות במדד (Apple, Microsoft, Amazon, NVIDIA, Google) מהוות כ-40% ממשקלו, האם הקרן חשופה יתר על המידה לסיכון ריכוזיות?",
          "answer": "הריכוזיות הגבוהה ב-QQQ פירושה שביצועי הקרן תלויים מאוד בקומץ חברות ענק. למרות שהן חברות חזקות, סיכון הריכוזיות קיים ותנודות חדות באחת מהן יכולות להשפיע באופן ניכר על הקרן כולה.",
          "implication": "שלילי"
        },
        {
          "question": "האם דמי הניהול של QQQ (0.20%) נחשבים תחרותיים, והאם הנזילות היומית הגבוהה מאפשרת כניסה ויציאה חלקה גם בתקופות תנודתיות גבוהה בשוק?",
          "answer": "דמי ניהול של 0.20% הם תחרותיים מאוד ונמוכים. הנזילות האדירה של QQQ (מחזורי מסחר של מיליוני מניות ביום) מבטיחה פיזור פקודות יעיל ומינימום סליפג' גם בימי מסחר סוערים.",
          "implication": "חיובי"
        },
        {
          "question": "כיצד תשפיע ירידה פוטנציאלית במדד הפחד (VIX) מתחת לרמה של 12 נקודות על סנטימנט המשקיעים ב-QQQ, ובהתחשב בהיותה קרן צמיחה?",
          "answer": "ירידה ב-VIX לרמות נמוכות מ-12 נקודות תצביע על ירידה בפחד ועלייה בביטחון המשקיעים, מה שיועיל לקרנות צמיחה כמו QQQ. סביבה של סיכון נמוך מעודדת השקעה במניות טכנולוגיה.",
          "implication": "חיובי"
        }
      ],
      "buzz_alert": "הבאז סביב QQQ מושפע ישירות מהסנטימנט הכללי בשוק הטכנולוגיה. ירידה של 1.26% היום עשויה לעורר דיונים על מימוש רווחים לאחר ריצה ארוכה. חלק מהרעש מגיע מאנליסטים המנתחים את דוחות חברות הטכנולוגיה, אך גם סוחרים קצרי טווח המגיבים לתנודות יומיות. ההשפעה הכוללת היא של זהירות אך ללא פאניקה, לאור העליות המשמעותיות שהיו לאחרונה.",
      "sources": [
        "https://finance.yahoo.com/quote/QQQ/",
        "https://www.invesco.com/us/financial-products/etfs/product-detail?ticker=QQQ",
        "https://seekingalpha.com/symbol/QQQ",
        "https://finviz.com/quote.ashx?t=QQQ",
        "https://www.etf.com/QQQ"
      ],
      "analysis_type": "short",
      "market": "US",
      "price": 704.3,
      "change_pct": -1.26,
      "analyst_ratings": {
        "strongBuy": 0,
        "buy": 0,
        "hold": 0,
        "sell": 0,
        "strongSell": 0
      }
    },
    {
      "ticker": "URNM",
      "company_name": "קרן סל כורי אורניום של Sprott",
      "sector": "חומרים בסיסיים",
      "signal": "תיקון חד, פוטנציאל איסוף",
      "direction": "bullish",
      "confidence": 75,
      "earnings_insight": "כקרן סל, ל-URNM אין דוחות רווחים קלאסיים. עם זאת, ביצועי הקרן קשורים ישירות למחירי האורניום ולביצועי החברות המוחזקות בה. הירידה של 4.72% היום משקפת ככל הנראה תיקון במחיר האורניום הספוט או מימוש רווחים לאחר תקופה של עליות. הקרן שואפת לחשוף את המשקיעים לחברות העוסקות בכרייה, חיפוש וייצור אורניום. כל שינוי במדיניות אנרגיה גרעינית או אירועים גיאופוליטיים משפיעים ישירות על נכסיה וביצועיה.",
      "bottom_line": "יש לנטר את רמת 64 דולר כאזור איסוף פוטנציאלי, עם יעד נזילות ראשון סביב 68 דולר ונקודת ביטול תזה חדה ב-62 דולר, המגלמת יחס סיכוי/סיכון של 2:1.",
      "catalysts": [
        {
          "type": "sector",
          "title": "התאוששות במחיר האורניום",
          "description": "URNM מושפעת ישירות ממחיר האורניום. כל התאוששות במחיר הספוט של האורניום לאחר הירידה הנוכחית, או חדשות על הסכמי רכש גדולים של אורניום על ידי חברות חשמל, יכולות לשמש כקטליזטור מיידי.",
          "impact": "חיובי",
          "timeframe": "מיידי/ימים"
        },
        {
          "type": "regulatory",
          "title": "מדיניות אנרגיה גרעינית",
          "description": "הכרזות על תמיכה ממשלתית מוגברת באנרגיה גרעינית (לדוגמה, סובסידיות, הקלות רגולטוריות או בניית כורים חדשים) במדינות מפתח, יכולות להגביר את הביקוש לאורניום ולשפר את סנטימנט השוק כלפי כורי אורניום.",
          "impact": "חיובי",
          "timeframe": "שבועות/חודשים"
        },
        {
          "type": "technical",
          "title": "תמיכה טכנית לאחר ירידה חדה",
          "description": "הירידה החדה של 4.72% היום מציבה את URNM על רמות תמיכה טכניות. בלימה באזורים אלה, במיוחד סביב 64 דולר, יכולה להוביל לריבאונד קצר טווח כתוצאה מ'קניית הדיפ' וכיסוי שורטים.",
          "impact": "חיובי",
          "timeframe": "מיידי"
        }
      ],
      "questions": [
        {
          "question": "בהינתן הירידה של 4.72% היום, ובהתחשב ש-URNM ירדה ב-23.5% מה-52w_high שלה (84.95 דולר), האם פיזור המניות בקרן מספיק כדי להגן מפני תנודתיות במניות בודדות?",
          "answer": "URNM מפזרת את ההשקעה על פני מספר כורי אורניום, אך הסקטור כולו נוטה להיות תנודתי. הירידה המשמעותית מהשיא מצביעה על כך שלמרות הפיזור, הקרן עדיין רגישה למגמות סקטוריאליות רחבות ולתנודות במחיר הסחורה. יש לבחון את ריכוזיות המניות המובילות בקרן.",
          "implication": "ניטרלי"
        },
        {
          "question": "האם דמי הניהול של URNM, העומדים על 0.85%, נחשבים סבירים בהשוואה לדמי ניהול של 0.2% ומטה בקרנות סל אחרות, וכיצד הם משפיעים על התשואה נטו של המשקיע?",
          "answer": "דמי ניהול של 0.85% נחשבים גבוהים יחסית לקרנות סל רחבות, אך מקובלים יותר בקרנות סקטוריאליות נישתיות כמו אורניום. דמי הניהול מפחיתים את התשואה נטו של המשקיע באופן ישיר. משקיעים צריכים לשקול אם החשיפה הייחודית לסקטור מצדיקה את העלות הגבוהה יותר לעומת קרנות בעלות דמי ניהול נמוכים יותר.",
          "implication": "שלילי"
        },
        {
          "question": "בהינתן שהקרן 'לא מגוונת' (non-diversified) ומתמקדת בכורי אורניום, מהו המשקל של 10 המניות הגדולות ביותר ב-URNM, והאם זהו פיזור אמיתי או שהמשקיע קונה בעצם חשיפה מרוכזת לכמה חברות בודדות?",
          "answer": "כקרן סקטוריאלית לא מגוונת, URNM נוטה להיות מרוכזת יותר. יש לבדוק את ההחזקות העדכניות, אך לרוב, 10 המניות הגדולות יכולות להוות חלק משמעותי מהקרן. המשקיע מקבל פיזור מסוים בתוך הסקטור, אך עדיין חשוף לסיכונים ריכוזיים של חברות ספציפיות ולסיכון סקטוריאלי כולל, ולא פיזור רחב כמו בקרן מדד.",
          "implication": "ניטרלי"
        }
      ],
      "buzz_alert": "הבאז סביב URNM וסקטור האורניום הוא חזק ומונע ברובו על ידי תזה ארוכת טווח של מחסור באורניום ועלייה בביקוש לאנרגיה גרעינית. חלק ניכר מהרעש מגיע מקהילות משקיעים קמעונאיות ופורומים ייעודיים, שבהם יש נטייה להדגיש נרטיבים חיוביים ולעודד 'קניית הדיפ'. עם זאת, יש גם ניתוחים ממוקדים יותר לגבי היצע וביקוש. יש לזהות את ההפרדה בין נתונים עובדתיים (מחירי אורניום ספוט, הסכמי רכש) לבין שיווק (הבטחות לעתיד זוהר). ההשפעה על הלך הרוח היא של אופטימיות בסיסית, אך עם קבלת תנודתיות גבוהה.",
      "sources": [
        "https://finance.yahoo.com/quote/URNM/",
        "https://sprottetfs.com/urnm-etf/",
        "https://www.marketwatch.com/investing/fund/URNM",
        "https://etfdb.com/etf/URNM/"
      ],
      "analysis_type": "short",
      "market": "US",
      "price": 64.97,
      "change_pct": -4.72,
      "analyst_ratings": {
        "strongBuy": 0,
        "buy": 0,
        "hold": 0,
        "sell": 0,
        "strongSell": 0
      }
    },
    {
      "ticker": "STNG",
      "company_name": "סקרופיו טנקרס",
      "sector": "אנרגיה",
      "signal": "התאוששות לאחר משיכה קלה",
      "direction": "bullish",
      "confidence": 75,
      "earnings_insight": "דוחות קודמים הראו ביצועים פיננסיים חזקים, הנתמכים על ידי שיעורי הובלה גבוהים במיוחד במגזר מכליות הנפט. ההנהלה הדגישה את יכולת החברה לייצר תזרימי מזומנים משמעותיים ולהפחית חובות, מה שמוביל לתשואות גבוהות לבעלי המניות. למרות היסטוריה של תנודתיות, הסנטימנט סביב החברה נשאר חיובי בשל תנאי השוק הנוכחיים.",
      "bottom_line": "יש לעקוב אחר פריצה של רמת 87.39$ (שיא 52 שבועות); פריצה מוצלחת עם ווליום גבוה עשויה לסלול את הדרך ליעד המחיר של 99$.",
      "catalysts": [
        {
          "type": "sector",
          "title": "שיעורי הובלה חזקים בסקטור האנרגיה",
          "description": "סקטור מכליות הנפט ממשיך ליהנות משיעורי הובלה גבוהים, המונעים על ידי ביקוש עולמי לנפט ושיבושים גיאופוליטיים. זהו קטליזטור עסקי חזק התומך ברווחיות החברה ובביצועי המניה, למרות המשיכה הקלה של 0.79% היום.",
          "impact": "חיובי",
          "timeframe": "שבועות/חודשים"
        },
        {
          "type": "technical",
          "title": "בלימה טכנית לפני שיא 52 שבועות",
          "description": "הירידה הקלה היום (0.79%) מהווה משיכה טכנית בריאה לאחר התקרבות לשיא 52 השבועות (87.39$). זו הזדמנות לקונים חדשים להיכנס, וצפויה התאוששות מהירה לכיוון השיא אם הסנטימנט החיובי יישמר.",
          "impact": "חיובי",
          "timeframe": "ימים"
        },
        {
          "type": "squeeze",
          "title": "לחץ על שורטיסטים",
          "description": "עם יחס PE נמוך ופוטנציאל עלייה משמעותי למחיר היעד של 99$, שורטיסטים שנכנסו לפוזיציות יתקשו להחזיק. פריצה של 87.39$ עלולה להפעיל שורט סקוויז ולדחוף את המחיר במהירות כלפי מעלה ב-5-10%.",
          "impact": "חיובי",
          "timeframe": "ימים"
        }
      ],
      "questions": [
        {
          "question": "בהינתן שמחיר המניה ירד ב-0.79% היום, האם קו ה-VWAP שימש כרמת תמיכה במהלך המסחר, מה שמעיד על כוח קנייה בתוך היום?",
          "answer": "אם המחיר נשאר מעל ה-VWAP או ביצע ריבאונד ממנו, זה מחזק את התזה שהמשיכה היא זמנית וכי קיים עניין קנייה. שבירה מתחת ל-VWAP תעיד על חולשה פוטנציאלית.",
          "implication": "ניטרלי"
        },
        {
          "question": "עם יחס חוב להון עצמי של 17.044, האם ישנם דיווחים עדכניים על מאמצי החברה להפחית חובות נוספים, מה שיכול לשמש כקטליזטור חיובי?",
          "answer": "הפחתת חובות משפרת את יציבות החברה ומגדילה את האטרקטיביות שלה למשקיעים. דיווחים כאלה יכולים להוסיף קטליזטור חיובי נוסף למניה ולתמוך בעליית המחיר מעבר לביצועי הסקטור.",
          "implication": "חיובי"
        }
      ],
      "buzz_alert": "הבאז סביב STNG נשאר חיובי מאוד, מונע על ידי דיווחים על שיעורי הובלה גבוהים וביקוש יציב לנפט. משקיעים רבים רואים במניה הזדמנות להשקעה בסקטור האנרגיה עם PE נמוך (8.34). אין עדויות למניפולציה, אך יש לזכור שהבאז משקף את הסנטימנט הכללי החיובי שעלול להשתנות במהירות עם שינויים בשוק הספנות או במחירי הנפט. ההשפעה היא תמיכה בסנטימנט חיובי ועידוד קנייה.",
      "sources": [
        "https://finance.yahoo.com/quote/STNG/",
        "https://seekingalpha.com/symbol/STNG",
        "https://www.sec.gov/cgi-bin/browse-edgar?action=getcompany&CIK=0001464309&type=10-Q",
        "https://finviz.com/quote.ashx?t=STNG",
        "https://www.reuters.com/companies/STNG.N"
      ],
      "analysis_type": "short",
      "market": "US",
      "price": 84.48,
      "change_pct": -0.79,
      "price_target": {
        "mean": 99.0,
        "low": 87.0,
        "high": 120.0,
        "num_analysts": 9
      }
    },
    {
      "ticker": "ASML",
      "company_name": "ASML אחזקות",
      "sector": "טכנולוגיה",
      "signal": "תיקון טכני, הזדמנות איסוף",
      "direction": "bullish",
      "confidence": 70,
      "earnings_insight": "בדוח הרבעוני האחרון (Q1 2024), ASML הציגה הזמנות חדשות חזקות מהצפוי, במיוחד למערכות EUV מתקדמות, מה שהפתיע לטובה את השוק לאור החששות מהאטה. ההנהלה הדגישה את הביקוש המתמשך לטכנולוגיית AI ו-HPC כמנוע צמיחה, אך גם ציינה זהירות לגבי מחזור ההוצאות לטווח הקצר של הלקוחות. שינוי משמעותי הוא ההתמקדות בהגדלת כושר הייצור כדי לעמוד בביקוש העתידי, מה שמעיד על אמון ההנהלה בצמיחה ארוכת טווח.",
      "bottom_line": "יש לנטר את רמת 1500 דולר כאזור איסוף פוטנציאלי לטווח קצר, עם יעד נזילות ראשון סביב 1550 דולר ונקודת ביטול תזה חדה ב-1485 דולר, המגלמת יחס סיכוי/סיכון של 2.33:1.",
      "catalysts": [
        {
          "type": "technical",
          "title": "תיקון טכני ורמות תמיכה",
          "description": "הירידה של 3.35% היום מציבה את ASML קרוב לרמת תמיכה טכנית משמעותית סביב 1500 דולר, שהייתה בעבר אזור התנגדות. בלימה באזור זה יכולה לאותת על סיום התיקון קצר הטווח.",
          "impact": "חיובי",
          "timeframe": "מיידי/ימים"
        },
        {
          "type": "sector",
          "title": "סנטימנט סקטור השבבים",
          "description": "ASML מושפעת עמוקות מסנטימנט סקטור המוליכים למחצה. כל חדשות חיוביות מחברות שבבים מובילות או תחזיות אופטימיות מצד מוסדות פיננסיים לגבי הביקוש לשבבי AI יכולות לשמש כקטליזטור מיידי לעלייה.",
          "impact": "חיובי",
          "timeframe": "ימים"
        },
        {
          "type": "macro",
          "title": "שינוי בריבית הפדרלית",
          "description": "הציפיות להפחתת ריבית בארה\"ב או באירופה יכולות להגביר את התיאבון לסיכון ולהזרים הון למניות צמיחה כמו ASML, תוך הפחתת עלות ההון לחברות והגברת ההשקעות בתשתית טכנולוגית.",
          "impact": "חיובי",
          "timeframe": "שבועות/חודשים"
        }
      ],
      "questions": [
        {
          "question": "כיצד עמידות רמת התמיכה סביב 1500 דולר, לאור ירידה של 3.35% היום, תשפיע על המומנטום קצר הטווח של ASML?",
          "answer": "אם ASML תצליח לבלום מעל 1500 דולר, זה יאותת על חוזק קונים באזור זה ועל פוטנציאל לריבאונד טכני. שבירה מטה תעיד על לחץ מכירות נוסף ועלולה לפתוח פתח לירידות חדות יותר לעבר 1450 דולר.",
          "implication": "ניטרלי"
        },
        {
          "question": "האם יחס ה-PE העתידי של ASML העומד על 31.43 מצדיק את הסיכון להשקעה בטווח הקצר, בהינתן התנודתיות הנוכחית בסקטור המוליכים למחצה?",
          "answer": "יחס PE עתידי של 31.43 נחשב גבוה אך משקף ציפיות צמיחה חזקות. בטווח הקצר, הוא מותיר מעט מרווח טעות. כל שינוי שלילי בתחזיות ההכנסות או בביקוש למערכות EUV עלול להוביל לתיקון חד ביחס השווי, בעוד המשך צמיחה חזקה יכול להצדיק את הפרמיה.",
          "implication": "ניטרלי"
        },
        {
          "question": "בהינתן ש-ASML ירדה ב-3.35% היום בעוד מדד הטכנולוגיה הרחב ירד פחות, האם זה מצביע על חולשה ספציפית או על מימוש רווחים לאחר עליות חדות?",
          "answer": "ירידה חדה יחסית למדד יכולה להצביע על מימוש רווחים אגרסיבי במניה שעלתה רבות (52w_high: 1595.31), או על חששות ספציפיים שהתעוררו לגבי החברה או תת-סקטור הציוד לייצור שבבים. נדרש לבחון חדשות ספציפיות ל-ASML או ללקוחותיה הגדולים.",
          "implication": "שלילי"
        }
      ],
      "buzz_alert": "הבאז סביב ASML מתמקד בעיקר בתפקידה המרכזי בשרשרת אספקת השבבים ובביקוש ל-AI. חלק ניכר מהשיח מגיע מאנליסטים מוסדיים ופרשני תעשייה, אשר לרוב אינם בעלי עניין ישיר במניה בטווח הקצר. עם זאת, כל ירידה במחיר מנוצלת על ידי משקיעים פרטיים ומשפיעני רשת להדגשת ה'הזדמנות' ארוכת הטווח, מה שעלול ליצור רעש שיווקי המעודד קנייה. ההשפעה על הלך הרוח היא של אופטימיות זהירה, אך הירידה הנוכחית ממתנת את ההתלהבות ומעודדת בחינה מחודשת של רמות כניסה.",
      "sources": [
        "https://finance.yahoo.com/quote/ASML/",
        "https://seekingalpha.com/symbol/ASML",
        "https://www.sec.gov/cgi-bin/browse-edgar?action=getcompany&CIK=0000931276&type=20-F",
        "https://www.marketwatch.com/investing/stock/ASML"
      ],
      "analysis_type": "short",
      "market": "US",
      "price": 1513.39,
      "change_pct": -3.35,
      "price_target": {
        "mean": 1672.1127,
        "low": 907.8151,
        "high": 2015.9202,
        "num_analysts": 15
      }
    },
    {
      "ticker": "ISRG",
      "company_name": "אינטואיטיב סרג'יקל",
      "sector": "שירותי בריאות",
      "signal": "התאוששות מ-52 שבועות שפל",
      "direction": "bullish",
      "confidence": 70,
      "earnings_insight": "דוחות רבעוניים קודמים הצביעו על צמיחה חזקה בהליכים ובמכירת מערכות דה-וינצ'י, אך גם על לחץ תחרותי והשפעת סביבת הריבית על הוצאות בתי חולים. ההנהלה הדגישה את ההשקעה במוצרים חדשים ובשוקי צמיחה בינלאומיים ככיוון אסטרטגי. התוצאות הפתיעו לטובה לעיתים קרובות בצד הרווחיות, אך צמיחת ההכנסות הייתה לעיתים תנודתית.",
      "bottom_line": "יש לעקוב אחר רמת 417.74$ כרמת תמיכה קריטית; פריצה מעליה עם ווליום עשויה לאותת על המשך מומנטום חיובי בטווח הקצר.",
      "catalysts": [
        {
          "type": "technical",
          "title": "ריבאונד טכני מ-52 שבועות שפל",
          "description": "המחיר הנוכחי של 429.01$ מציג עלייה של 2.13% ומתרחק מרמת השפל של 52 השבועות (417.74$). זוהי תגובה טכנית חיובית המעידה על כניסת קונים לרמות מחיר אטרקטיביות, וייתכן שהמחיר מצא תחתית זמנית.",
          "impact": "חיובי",
          "timeframe": "מיידי"
        },
        {
          "type": "squeeze",
          "title": "פוטנציאל שורט סקוויז",
          "description": "בהתחשב שהמניה נסחרה קרוב לשפל של 52 שבועות, סוחרים רבים יכלו להיכנס לפוזיציות שורט. עלייה מתמשכת מעל 430$ עשויה להפעיל כיסוי שורטים ולדחוף את המחיר במהירות כלפי מעלה, עם פוטנציאל לזינוק של 3-5% תוך זמן קצר.",
          "impact": "חיובי",
          "timeframe": "ימים"
        },
        {
          "type": "sentiment",
          "title": "סנטימנט 'קנה בירידה'",
          "description": "הנרטיב ברשתות החברתיות ובפורומים מראה עלייה בסנטימנט חיובי סביב המניה, כאשר משקיעים רבים רואים את המחיר הנוכחי כהזדמנות קנייה. זה יכול ליצור מומנטום חיובי נוסף ולתמוך בעליית המחיר.",
          "impact": "חיובי",
          "timeframe": "ימים"
        }
      ],
      "questions": [
        {
          "question": "האם העלייה של 2.13% היום מלווה בווליום מסחר גבוה משמעותית מהממוצע של 30 הימים האחרונים?",
          "answer": "עלייה בווליום לצד עליית מחיר תאשש את כניסת הכסף הגדול ותחזק את התזה שהריבאונד נובע מביקוש אמיתי ולא רק מתיקון טכני קצר טווח. ווליום נמוך עלול להעיד על חולשה פוטנציאלית של הריבאונד.",
          "implication": "חיובי"
        },
        {
          "question": "בהינתן שמחיר היעד הממוצע של אנליסטים הוא 577$, מהן רמות ההתנגדות הטכניות הקרובות שעלולות להאט את העלייה לאחר הריבאונד מ-417.74$?",
          "answer": "רמות התנגדות ראשוניות עשויות להיות סביב 435-440$, ולאחר מכן באזור 450-460$ שהיו נקודות תמיכה או התנגדות בעבר. פריצת רמות אלו תאותת על כוח קנייה משמעותי.",
          "implication": "ניטרלי"
        }
      ],
      "buzz_alert": "הבאז ברשתות החברתיות מתמקד ב'קניית הירידות' לאחר התקרבות למחיר השפל של 52 השבועות. נרטיב זה נתמך על ידי אנליסטים שממליצים על יעד מחיר גבוה יותר משמעותית (577$) ורואים את החברה כמובילה בתחום. עם זאת, יש לזכור שחלק מהבאז יכול להיות מופעל על ידי משקיעים המעוניינים לראות את המחיר עולה לאחר שנכנסו לפוזיציות. ההשפעה היא יצירת סנטימנט חיובי שעלול למשוך קונים נוספים בטווח הקצר.",
      "sources": [
        "https://finance.yahoo.com/quote/ISRG/",
        "https://seekingalpha.com/symbol/ISRG",
        "https://www.sec.gov/cgi-bin/browse-edgar?action=getcompany&CIK=0001035261&type=10-Q",
        "https://finviz.com/quote.ashx?t=ISRG",
        "https://openinsider.com/screener?s=ISRG"
      ],
      "analysis_type": "short",
      "market": "US",
      "price": 429.01,
      "change_pct": 2.13,
      "price_target": {
        "mean": 577.00934,
        "low": 378.0,
        "high": 750.0,
        "num_analysts": 30
      }
    },
    {
      "ticker": "SMH",
      "company_name": "קרן סל VanEck Semiconductor",
      "sector": "לא ידוע",
      "signal": "תיקון סקטוריאלי חד",
      "direction": "bearish",
      "confidence": 70,
      "earnings_insight": "כקרן סל, אין לה דוחות רבעוניים משלה, אך ביצועיה מושפעים מדוחות החברות המרכיבות אותה (כמו אנבידיה, TSMC, ASML). דוחות אחרונים של חברות אלו הציגו צמיחה חזקה, במיוחד בתחום ה-AI, אך גם חששות לגבי הערכות שווי גבוהות ופוטנציאל להאטה בביקוש עתידי בחלקים אחרים של השוק.",
      "bottom_line": "הירידה של 3.24% היום מצביעה על מומנטום שלילי בסקטור השבבים. יש לעקוב אחר רמת 550$ כתמיכה ראשונית. שבירה שלה עלולה להוביל לירידות חדות יותר.",
      "catalysts": [
        {
          "type": "sector",
          "title": "מימוש רווחים בסקטור השבבים",
          "description": "הירידה המשמעותית של 3.24% היום מצביעה על מימוש רווחים נרחב בסקטור השבבים כולו, לאחר תקופה של עליות חדות. משקיעים מנצלים את רמות השיא כדי לצאת מפוזיציות, מה שיוצר לחץ מכירה.",
          "impact": "שלילי",
          "timeframe": "מיידי"
        },
        {
          "type": "macro",
          "title": "חששות מאקרו גלובליים",
          "description": "סקטור השבבים רגיש מאוד למצב הכלכלה העולמית ולשינויים בביקוש למוצרי צריכה וטכנולוגיה. הירידה עשויה לשקף חששות גוברים לגבי האטה כלכלית עולמית או השפעת הריבית הגבוהה על הוצאות תאגידים וצרכנים.",
          "impact": "שלילי",
          "timeframe": "ימים"
        },
        {
          "type": "technical",
          "title": "שבירת תמיכה טכנית",
          "description": "ירידה חדה זו עלולה לשבור רמות תמיכה טכניות קריטיות, מה שיוביל להפעלת פקודות סטופ-לוס נוספות ולהאצת הירידה. רמת 550$ היא תמיכה פסיכולוגית וטכנית חשובה.",
          "impact": "שלילי",
          "timeframe": "מיידי"
        }
      ],
      "questions": [
        {
          "question": "בהינתן ירידה של 3.24% היום, מהו משקל 10 המניות הגדולות ביותר ב-SMH, והאם ירידה חדה באחת מהן (לדוגמה, אנבידיה) היא הגורם העיקרי לירידה בקרן הסל?",
          "answer": "SMH ידועה בריכוזיותה הגבוהה בכמה חברות ענק. ירידה משמעותית של 3.24% בקרן סל כזו יכולה להיות מונעת על ידי ירידה חדה במניה אחת או שתיים בעלות משקל גבוה. זיהוי המניה הספציפית יאפשר להבין את הקטליזטור המדויק.",
          "implication": "שלילי"
        },
        {
          "question": "האם הווליום של היום, המלווה בירידה של 3.24% ב-SMH, גבוה משמעותית מהממוצע של 30 הימים האחרונים, מה שמעיד על יציאת כסף מוסדי מהסקטור?",
          "answer": "ווליום גבוה בירידה חדה מצביע על כך שמוסדות מממשים רווחים או מפחיתים חשיפה לסקטור השבבים. זהו סימן שלילי המעיד על שינוי סנטימנט רחב יותר בקרב השחקנים הגדולים בשוק.",
          "implication": "שלילי"
        },
        {
          "question": "בהינתן שדמי הניהול של SMH הם בדרך כלל סבירים (מתחת ל-0.2% על פי ההנחיות), האם הנזילות היומית של הקרן מספיקה כדי למנוע spread אלים במקרה של יציאת פאניקה?",
          "answer": "SMH היא קרן סל גדולה ונסחרת בנזילות גבוהה מאוד, עם מחזורי מסחר יומיים של מיליארדי דולרים. גם בימי ירידות חדות, הספראד (הפרש קניה/מכירה) צפוי להישאר צר יחסית, מה שמאפשר יציאה מהפוזיציה ללא עיוותי מחיר משמעותיים.",
          "implication": "ניטרלי"
        }
      ],
      "buzz_alert": "הבאז סביב סקטור השבבים היה חיובי ביותר, מונע על ידי טירוף ה-AI. הירידה של היום (3.24%) עשויה ליצור פאניקה וסנטימנט שלילי ברשתות החברתיות, עם דיונים על 'בועה' ומימוש רווחים. יש לזהות אם הבאז השלילי מגיע ממקורות מבוססים (חדשות כלכליות) או מספקולציות של סוחרים קטנים. ההשפעה המיידית היא הגברת לחץ המכירה.",
      "sources": [
        "https://finance.yahoo.com/quote/SMH/",
        "https://www.vaneck.com/us/en/investments/semiconductor-etf-smh/",
        "https://seekingalpha.com/symbol/SMH",
        "https://finviz.com/quote.ashx?t=SMH"
      ],
      "analysis_type": "short",
      "market": "US",
      "price": 557.62,
      "change_pct": -3.24,
      "analyst_ratings": {
        "strongBuy": 0,
        "buy": 0,
        "hold": 0,
        "sell": 0,
        "strongSell": 0
      }
    },
    {
      "ticker": "LNG",
      "company_name": "Cheniere Energy, Inc.",
      "sector": "אנרגיה",
      "signal": "מומנטום חיובי",
      "direction": "bullish",
      "confidence": 70,
      "earnings_insight": "בדוח הרבעון הראשון לשנת 2024 (פורסם ב-1 במאי), שנאר Energy עקפה את תחזיות הרווח למניה אך החמיצה במעט את תחזיות ההכנסות. ההנהלה העלתה את תחזית הרווח המתואם לשנת 2024, מה שסיפק גב חזק למניה והדגיש את הביקוש המתמשך ל-LNG.",
      "bottom_line": "אזור איסוף: 242-244 דולר | יעד נזילות ראשון: 248-250 דולר | נקודת ביטול תזה: 239.5 דולר | יחס סיכוי/סיכון: 1.5:1",
      "catalysts": [
        {
          "type": "business",
          "title": "עסקאות יצוא LNG חדשות",
          "description": "על רקע המתיחות הגיאופוליטית והביקוש הגובר לאנרגיה באירופה ובאסיה, חתימה על חוזי יצוא LNG חדשים או הרחבת חוזים קיימים יכולה להוות קטליזטור חיובי משמעותי עבור Cheniere.",
          "impact": "חיובי",
          "timeframe": "ימים/שבועות"
        },
        {
          "type": "regulatory",
          "title": "שינויים במדיניות האנרגיה",
          "description": "כל התפתחות רגולטורית בארה\"ב בנוגע להיתרי יצוא LNG או מדיניות סביבתית יכולה להשפיע באופן ישיר על יכולת התפעול והרווחיות של Cheniere.",
          "impact": "לא ברור",
          "timeframe": "שבועות/חודשים"
        },
        {
          "type": "technical",
          "title": "פריצת התנגדות ב-248 דולר",
          "description": "המניה מתקרבת לרמת התנגדות טכנית סביב 248-250 דולר. פריצה משמעותית של רמה זו, הנתמכת על ידי מחזור מסחר גבוה, יכולה לאותת על המשך מגמת העלייה ולמשוך קונים נוספים.",
          "impact": "חיובי",
          "timeframe": "מיידי/ימים"
        }
      ],
      "questions": [
        {
          "question": "האם הביקוש הגלובלי ל-LNG ימשיך לגדול בקצב שיצדיק את ההשקעות בהרחבת כושר הייצור, בהתחשב בכך ש-Cheniere צופה גידול ב-Adjusted EBITDA של 10% ב-2024?",
          "answer": "התחזית החיובית של Cheniere ל-2024 נתמכת על ידי ביקוש יציב מאירופה ואסיה, אך התנודתיות במחירי הגז הטבעי והתחרות הגוברת מצד ספקיות LNG אחרות דורשות מעקב צמוד. התרחבות נוספת תלויה ביציבות הביקוש העולמי.",
          "implication": "ניטרלי"
        },
        {
          "question": "כיצד תשפיע רמת החוב הגבוהה של Cheniere (יחס חוב להון עצמי של כ-321%) על יכולתה לממן פרויקטים עתידיים או להתמודד עם עליית ריבית בסביבת המאקרו הנוכחית?",
          "answer": "למרות יחס החוב הגבוה, לחברה יש תזרימי מזומנים חזקים (FCF של כ-1.7 מיליארד דולר) המאפשרים לה לשרת את החוב ולממן פרויקטים. עם זאת, עליית ריבית משמעותית עלולה להגדיל את עלויות המימון ולפגוע ברווחיות העתידית.",
          "implication": "שלילי"
        },
        {
          "question": "האם נראה המשך של זרימת כסף מוסדי לאזורי הביד סביב רמת ה-VWAP של היום, לאור העלייה של 1.41% במניה?",
          "answer": "עלייה במחיר עם מחזור מסחר גבוה מעל ה-VWAP מצביעה על עניין מוסדי. אם המחיר יישאר מעל ה-VWAP ויציג תמיכה באזורי הביד, זה יאותת על כוונת קנייה מתמשכת של כסף גדול, מה שיכול לדחוף את המניה גבוה יותר.",
          "implication": "חיובי"
        }
      ],
      "buzz_alert": "הבאז סביב LNG מתמקד בעיקר במתיחות הגיאופוליטית ובביקוש האירופי המתמשך לגז טבעי נוזלי, במיוחד לקראת החורף. חלק מהרעש מגיע מאנליסטים ובתי השקעות המעלים מחירי יעד, אך יש לבחון בזהירות גם את ההשפעה של ספקולנטים קצרי טווח המגיבים לחדשות נקודתיות. ההשפעה הכוללת היא חיובית, ומחזקת את הנרטיב של LNG כספקית אנרגיה קריטית.",
      "sources": [
        "https://finance.yahoo.com/quote/LNG/",
        "https://seekingalpha.com/symbol/LNG",
        "https://www.sec.gov/cgi-bin/browse-edgar?action=getcompany&CIK=0000806461&type=10-Q",
        "https://finviz.com/quote.ashx?t=LNG",
        "https://www.reuters.com/markets/companies/LNG.A/"
      ],
      "analysis_type": "short",
      "market": "US",
      "price": 244.09,
      "change_pct": 1.41,
      "price_target": {
        "mean": 303.13635,
        "low": 259.0,
        "high": 340.0,
        "num_analysts": 22
      }
    },
    {
      "ticker": "FCX",
      "company_name": "פריפורט-מכמורן",
      "sector": "חומרים בסיסיים",
      "signal": "תלוי נחושת, נטייה חיובית",
      "direction": "bullish",
      "confidence": 68,
      "earnings_insight": "בדוח הרבעוני האחרון (Q1 2024), פריפורט-מכמורן הציגה תוצאות חזקות, הנתמכות על ידי מחירי נחושת גבוהים וייצור יציב, במיוחד מנכסי Grasberg ו-Cerro Verde. ההנהלה הדגישה את הביקוש הגובר לנחושת כתוצאה מהמעבר לאנרגיה ירוקה ו-AI, והפתיעה לטובה עם תחזית ייצור אופטימית לשנה הקרובה. החברה ממשיכה להתמקד בהפחתת חוב ובהשקעות בגידול תפוקה. השינוי המרכזי הוא התחזקות התזה ארוכת הטווח לנחושת, למרות תנודתיות קצרת טווח.",
      "bottom_line": "יש לנטר את רמת 63 דולר כאזור איסוף פוטנציאלי, עם יעד נזילות ראשון סביב 66 דולר ונקודת ביטול תזה חדה ב-62 דולר, המגלמת יחס סיכוי/סיכון של 3:1.",
      "catalysts": [
        {
          "type": "sector",
          "title": "עלייה במחירי הנחושת",
          "description": "FCX רגישה מאוד למחירי הנחושת. כל עלייה משמעותית במחיר הנחושת העולמי, המונעת מביקוש מוגבר (למשל מתעשיית הרכב החשמלי או תשתית AI) או הפרעות באספקה, תשמש כקטליזטור חיובי ישיר.",
          "impact": "חיובי",
          "timeframe": "מיידי/ימים"
        },
        {
          "type": "macro",
          "title": "נתוני צמיחה מסין",
          "description": "סין היא הצרכנית הגדולה ביותר של נחושת. כל נתון מאקרו חיובי מסין (כמו נתוני PMI ייצור או גידול בתמ\"ג) שיעיד על התאוששות כלכלית, יכול להגביר את הביקוש לנחושת ולדחוף את מניית FCX מעלה.",
          "impact": "חיובי",
          "timeframe": "שבועות"
        },
        {
          "type": "business",
          "title": "התקדמות בפרויקטים חדשים",
          "description": "הכרזה על התקדמות משמעותית בפרויקטים חדשים או הרחבת מכרות קיימים, במיוחד באזורי מפתח כמו Grasberg, שיגדילו את כושר הייצור העתידי של נחושת, יכולה לשפר את תחזיות ההכנסות ולהוות קטליזטור.",
          "impact": "חיובי",
          "timeframe": "חודשים"
        }
      ],
      "questions": [
        {
          "question": "בהינתן נתון ה-PE העתידי של FCX העומד על 17.23, ובהשוואה למתחרות בסקטור, האם המניה מתומחרת בהגינות לאור התנודתיות במחירי הנחושת?",
          "answer": "PE עתידי של 17.23 נחשב סביר עבור חברת חומרים בסיסיים, אך הוא רגיש מאוד לתנודות במחירי הסחורות. אם מחירי הנחושת ימשיכו לעלות, ה-PE יכול להצטמצם ולהצדיק את השווי. אם מחירי הנחושת ירדו, ה-PE עלול להיראות יקר. נדרשת הערכה מתמדת של מחירי הסחורות.",
          "implication": "ניטרלי"
        },
        {
          "question": "כיצד הפוטנציאל העתידי לנחושת מביקוש מצד תעשיית הרכב החשמלי ותשתיות AI, משפיע על יעד המחיר הממוצע של אנליסטים העומד על 67.51 דולר?",
          "answer": "הביקוש לנחושת מתעשיות ה-EV וה-AI הוא גורם מפתח בתמיכה בתזת העלייה למחירי נחושת גבוהים יותר, מה שמתבטא ביעדי מחיר אופטימיים של אנליסטים. אם הביקוש בפועל יעלה על הציפיות, יעדי המחיר יכולים להתעדכן כלפי מעלה, ולהפך.",
          "implication": "חיובי"
        },
        {
          "question": "בהינתן יחס החוב להון (Debt-to-Equity) הגבוה יחסית של FCX העומד על 33.008, כיצד החברה מתכננת לנהל את החוב שלה בתקופה של ריביות גבוהות?",
          "answer": "יחס חוב להון של 33.008 הוא גבוה אך לא חריג לחברות כרייה עתירות הון. החברה תצטרך להמשיך להפחית חוב ולנהל את הוצאות הריבית ביעילות. בתקופה של ריביות גבוהות, עלות החוב עולה, מה שעלול לפגוע ברווחיות. עם זאת, אם מחירי הנחושת נשארים גבוהים, תזרים המזומנים החזק יכול לסייע בכיסוי החוב.",
          "implication": "ניטרלי"
        }
      ],
      "buzz_alert": "הבאז סביב FCX קשור קשר הדוק לשוק הסחורות, ובפרט למחירי הנחושת. רוב השיח מגיע מאנליסטים של סחורות, מוסדות פיננסיים ובלוגים המתמקדים במאקרו כלכלה. ישנה הבחנה ברורה בין נתונים עובדתיים (מלאי נחושת, נתוני ייצור) לבין ספקולציות לגבי הביקוש העתידי. ההשפעה על הלך הרוח היא של אופטימיות זהירה, עם הכרה בכך שהנחושת היא חומר גלם קריטי לעתיד, אך גם חשש מתנודתיות מחירים ומהאטה כלכלית עולמית. אין עדויות משמעותיות למניפולציה או 'ספוּפינג' בולטים.",
      "sources": [
        "https://finance.yahoo.com/quote/FCX/",
        "https://seekingalpha.com/symbol/FCX",
        "https://www.sec.gov/cgi-bin/browse-edgar?action=getcompany&CIK=00000831259&type=10-Q",
        "https://www.marketwatch.com/investing/stock/FCX"
      ],
      "analysis_type": "short",
      "market": "US",
      "price": 63.9,
      "change_pct": -0.73,
      "price_target": {
        "mean": 67.51905,
        "low": 31.0,
        "high": 76.0,
        "num_analysts": 21
      }
    },
    {
      "ticker": "PLTR",
      "company_name": "פלנטיר טכנולוגיות",
      "sector": "טכנולוגיה",
      "signal": "איסוף בדיפ, פוטנציאל סחיטה",
      "direction": "bullish",
      "confidence": 65,
      "earnings_insight": "בדוח הרבעוני האחרון (Q1 2024), פלנטיר הציגה צמיחה מרשימה במגזר המסחרי בארה\"ב של 69% ב-YoY, מה שהפתיע לטובה והצביע על הצלחה באסטרטגיית ה-bootcamps. ההנהלה הדגישה את הפוטנציאל העצום של פלטפורמת ה-AIP (Artificial Intelligence Platform) והכריזה על שותפויות חדשות. למרות שהרווחיות נותרה תחת זכוכית מגדלת עם PE של 151.61, החברה ממשיכה להציג FCF חיובי, מה שמחזק את האמון ביכולתה לממן צמיחה עתידית. השינוי המרכזי הוא המעבר מפרויקטים ממשלתיים גדולים לצמיחה מהירה במגזר הפרטי והתעשייתי.",
      "bottom_line": "יש לנטר את רמת 133 דולר כאזור איסוף פוטנציאלי, עם יעד נזילות ראשון סביב 140 דולר ונקודת ביטול תזה חדה ב-130 דולר, המגלמת יחס סיכוי/סיכון של 2.33:1.",
      "catalysts": [
        {
          "type": "business",
          "title": "חוזים ממשלתיים חדשים",
          "description": "פלנטיר ידועה בחוזיה עם גופים ממשלתיים. כל הכרזה על חוזה גדול חדש, במיוחד בתחום הביטחון או המודיעין, יכולה לשמש כקטליזטור מיידי חיובי, כפי שקרה בעבר עם חוזים עם צבא ארה\"ב או משרד הבריאות הבריטי.",
          "impact": "חיובי",
          "timeframe": "מיידי/ימים"
        },
        {
          "type": "technical",
          "title": "רמות תמיכה טכניות",
          "description": "הירידה של 1.38% היום מקרבת את PLTR לרמת תמיכה משמעותית סביב 133-134 דולר. בלימה ועצירה באזור זה יכולה לאותת על כניסת קונים והזדמנות לריבאונד טכני, במיוחד לאור ה-52w_low ב-118.93 דולר.",
          "impact": "חיובי",
          "timeframe": "מיידי"
        },
        {
          "type": "squeeze",
          "title": "פוטנציאל סחיטת שורטיסטים",
          "description": "אם PLTR תפרוץ מעל רמת ההתנגדות סביב 140 דולר, סוחרים רבים שנכנסו לשורט ימצאו עצמם בפוזיציה מפסידה וייאלצו לכסות, מה שיוביל לסחיטת שורטיסטים (Short Squeeze) ולהאצה של העלייה. רמות אלה נבנות מעל אזורי התנגדות קודמים.",
          "impact": "חיובי",
          "timeframe": "ימים"
        }
      ],
      "questions": [
        {
          "question": "בהינתן יחס ה-PE הגבוה של PLTR העומד על 151.61, האם צמיחת ההכנסות במגזר המסחרי, שעמדה על 69% ב-YoY בדוח האחרון, מספיקה כדי להצדיק את השווי הנוכחי?",
          "answer": "צמיחה של 69% במגזר המסחרי היא מרשימה, אך יחס PE כה גבוה מצביע על כך שהשוק כבר מתמחר צמיחה אגרסיבית מאוד קדימה. כל האטה בצמיחה או אי-עמידה בציפיות עלולה להוביל לתיקון חד במחיר המניה, בעוד המשך צמיחה בקצב דומה יכול להצדיק את הפרמיה.",
          "implication": "ניטרלי"
        },
        {
          "question": "האם הירידה של 1.38% היום, יחד עם נתון ה-52w_high ב-207.52 דולר, מעידה על מימוש רווחים טבעי או על שינוי בסנטימנט המשקיעים כלפי מניות AI?",
          "answer": "הירידה הנוכחית, לאחר עליות משמעותיות שהובילו ל-52w_high של 207.52, יכולה להיות מימוש רווחים טבעי. עם זאת, יש לבחון את הרוחב של הירידות בסקטור ה-AI כולו כדי לקבוע אם מדובר בשינוי סנטימנט רחב יותר או בתנועה ספציפית למניה.",
          "implication": "ניטרלי"
        },
        {
          "question": "כיצד השותפות האסטרטגית של PLTR עם Ondas Inc. לפיתוח יכולות ISR מבוססות AI תשפיע על פוטנציאל הצמיחה העתידי של החברה, במיוחד במגזר הביטחוני?",
          "answer": "שותפות זו יכולה לפתוח שווקים חדשים ולהרחיב את יכולותיה של PLTR בתחום המודיעין, מעקב וסיור (ISR), מה שיכול להגדיל את בסיס הלקוחות הממשלתי והביטחוני. ההשפעה תלויה בהצלחת הפיתוח ובקצב האימוץ של הטכנולוגיה החדשה, אך היא מצביעה על כיווני צמיחה עתידיים.",
          "implication": "חיובי"
        }
      ],
      "buzz_alert": "הבאז סביב PLTR הוא מהגבוהים בשוק, מונע בעיקר מההתלהבות סביב AI והמעורבות של החברה בפרויקטים ממשלתיים רגישים. חלק ניכר מהרעש מגיע ממשקיעים קמעונאיים ו'משפיעני AI' בעלי אינטרס בקידום המניה, וכן מבלוגים טכנולוגיים. יש הפרדה ברורה בין העובדות (חוזים חדשים, צמיחה מסחרית) לבין שיווק (הבטחות עתידיות למהפכת AI). ההשפעה על הלך הרוח היא של אופטימיות מוגברת, אך גם רגישות גבוהה לכל חדשה שלילית או מימוש רווחים, מה שיוצר תנודתיות. יש לזהות אם בעלי עניין גדולים (אינסיידרים) מוכרים מניות בתיאום עם הבאז החיובי.",
      "sources": [
        "https://finance.yahoo.com/quote/PLTR/",
        "https://seekingalpha.com/symbol/PLTR",
        "https://openinsider.com/screener?s=PLTR",
        "https://www.sec.gov/cgi-bin/browse-edgar?action=getcompany&CIK=0001321655&type=10-Q"
      ],
      "analysis_type": "short",
      "market": "US",
      "price": 135.0,
      "change_pct": -1.38,
      "price_target": {
        "mean": 181.50667,
        "low": 70.0,
        "high": 255.0,
        "num_analysts": 27
      }
    },
    {
      "ticker": "PWR",
      "company_name": "קוואנטה סרוויסס",
      "sector": "תעשייה",
      "signal": "מימוש רווחים לאחר שיא",
      "direction": "bearish",
      "confidence": 65,
      "earnings_insight": "דוחות קודמים הראו צמיחה עקבית בהכנסות וברווחים, הנתמכים על ידי השקעות בתשתיות אנרגיה ותקשורת. ההנהלה הדגישה את חוזק הצבר ואת המגמות ארוכות הטווח לטובת החברה. עם זאת, יחס ה-PE הגבוה (104.69) מצביע על כך שציפיות צמיחה עתידיות כבר מגולמות במחיר, והפתעות שליליות עלולות להוביל לתגובה חריפה.",
      "bottom_line": "יש לשים לב לרמת 747.84$ (יעד מחיר אנליסטים) כרמת תמיכה פוטנציאלית. שבירה שלה עלולה להוביל לגל ירידות נוסף.",
      "catalysts": [
        {
          "type": "technical",
          "title": "מימוש רווחים משיא 52 שבועות",
          "description": "הירידה של 2.59% היום, לאחר שהמניה נסחרה קרוב לשיא של 52 שבועות (788.75$), מצביעה על מימוש רווחים משמעותי. סוחרים ומשקיעים מנצלים את רמות המחיר הגבוהות כדי לצאת מפוזיציות, מה שיוצר לחץ מכירה.",
          "impact": "שלילי",
          "timeframe": "מיידי"
        },
        {
          "type": "valuation",
          "title": "חששות הערכת שווי",
          "description": "עם יחס PE של 104.69, המניה מתומחרת בפרמיה גבוהה מאוד. ירידה זו עשויה להיות תגובה לחששות גוברים בשוק לגבי הערכת השווי הנוכחית, במיוחד אם אין קטליזטורים חיוביים חדשים שיצדיקו אותה.",
          "impact": "שלילי",
          "timeframe": "ימים"
        },
        {
          "type": "technical",
          "title": "שבירה מתחת ל-VWAP",
          "description": "אם המחיר נסחר כעת מתחת לקו ה-VWAP עם ווליום גבוה, זה מחזק את התזה של לחץ מכירה מוסדי. שבירה מתחת ל-VWAP מעידה על כך שהקונים של היום נמצאים בהפסד, מה שעלול להוביל ללחץ מכירה נוסף.",
          "impact": "שלילי",
          "timeframe": "מיידי"
        }
      ],
      "questions": [
        {
          "question": "האם הווליום של היום, המלווה בירידה של 2.59%, גבוה משמעותית מהממוצע של 30 הימים האחרונים, מה שמעיד על יציאת כסף מוסדי?",
          "answer": "ווליום גבוה בירידה מעיד על השתתפות מוסדית במימוש הרווחים. אם הווליום נמוך, הירידה עשויה להיות תיקון טכני קצר טווח או מימוש רווחים של סוחרים קטנים יותר, ולא בהכרח שינוי מגמה עמוק.",
          "implication": "שלילי"
        },
        {
          "question": "בהינתן שמחיר היעד הממוצע של האנליסטים (747.84$) נמוך מהמחיר הנוכחי (761.14$), האם ישנן רמות תמיכה משמעותיות לפני 747.84$ שיכולות לבלום את הירידה?",
          "answer": "רמות תמיכה פוטנציאליות עשויות להיות סביב 755$ או 750$, שהיו נקודות תמיכה או התנגדות קודמות. שבירה מתחת לרמות אלו תגביר את הלחץ לכיוון מחיר היעד של האנליסטים ואף נמוך יותר.",
          "implication": "שלילי"
        }
      ],
      "buzz_alert": "הבאז סביב PWR היה חיובי ביותר לאור ביצועי המניה החזקים והמעורבות בפרויקטי תשתית גדולים. עם זאת, הירידה של היום עשויה להתחיל לשנות את הסנטימנט, כאשר משקיעים מתחילים לתהות אם המניה הגיעה לשיא זמני. חשוב להבחין בין ההודעות החיוביות של החברה (עובדות) לבין ספקולציות ברשתות החברתיות בנוגע להמשך העליות (שיווק). ההשפעה המיידית היא חשש ממימוש רווחים נוסף.",
      "sources": [
        "https://finance.yahoo.com/quote/PWR/",
        "https://seekingalpha.com/symbol/PWR",
        "https://www.sec.gov/cgi-bin/browse-edgar?action=getcompany&CIK=0001007871&type=10-Q",
        "https://finviz.com/quote.ashx?t=PWR",
        "https://www.marketwatch.com/investing/stock/PWR"
      ],
      "analysis_type": "short",
      "market": "US",
      "price": 761.14,
      "change_pct": -2.59,
      "price_target": {
        "mean": 747.8408,
        "low": 420.0,
        "high": 901.0,
        "num_analysts": 24
      }
    },
    {
      "ticker": "SPY",
      "company_name": "קרן סל SPDR S&P 500 של סטייט סטריט",
      "sector": "מדד רחב",
      "signal": "התכנסות לפני הכרעה",
      "direction": "neutral",
      "confidence": 65,
      "earnings_insight": "דוחות הרווחים האחרונים של חברות ה-S&P 500 הציגו תמונה מעורבת אך בסך הכל חיובית, עם רוב החברות עוקפות את ציפיות האנליסטים הן בהכנסות והן ברווחים. עם זאת, התחזיות העתידיות של ההנהלות משקפות זהירות מסוימת לגבי קצב הצמיחה והשפעת הריביות הגבוהות, מה שמוביל לסנטימנט של 'בחינת נתונים' בשוק במקום דחיפה קדימה.",
      "bottom_line": {
        "entry_zone": "730.00 - 732.00",
        "take_profit": "740.00",
        "hard_stop_loss": "725.00",
        "rr_ratio": "1.5:1"
      },
      "buzz_alert": "הבאז סביב SPY מושפע בעיקר מכותרות מאקרו, נתוני כלכלה ופרשנויות של כלכלנים ומוסדות פיננסיים גדולים. ישנם פחות ניסיונות מניפולציה ישירים על SPY עצמו בשל גודלו ונזילותו העצומה, אך ספקולציות לגבי מדיניות הפד או נתוני אינפלציה יכולות ליצור תנודתיות רבה. משקיעים רבים עוקבים אחרי 'הגורו'ים' שמצביעים על כיוון השוק, אך יש לבחון כל טענה מול נתונים כלכליים קונקרטיים, שכן גם למוסדות יש אינטרסים מובהקים המשפיעים על הלך הרוח הכללי.",
      "sources": [
        "https://finance.yahoo.com/quote/SPY/",
        "https://www.ssga.com/us/en/individual/etfs/funds/spdr-sp-500-etf-trust-spy",
        "https://finviz.com/quote.ashx?t=SPY",
        "https://seekingalpha.com/symbol/SPY"
      ],
      "analysis_type": "short",
      "market": "US",
      "catalysts": [
        {
          "type": "macro",
          "title": "החלטת ריבית הפד הקרובה",
          "description": "השוק ממתין בציפייה להחלטת הריבית הבאה של הפדרל ריזרב ולנאום יו\"ר הפד. כל רמז לכיוון מדיניות מוניטרית עתידית – יוני (Hawkish) או יונית (Dovish) – ישפיע באופן ישיר על תמחור המניות במדד ה-S&P 500.",
          "impact": "לא ברור",
          "timeframe": "ימים"
        },
        {
          "type": "technical",
          "title": "התנגדות שיא של 52 שבועות",
          "description": "המדד נסחר קרוב מאוד לשיא של 52 השבועות (740.79). פריצה מעלה עם מחזור גבוה יכולה לשמש כקטליזטור חיובי לדחיפה נוספת, בעוד כישלון לפרוץ או דחייה חדה מהרמה הזו יכולים להוביל לתיקון קצר טווח.",
          "impact": "לא ברור",
          "timeframe": "מיידי"
        },
        {
          "type": "macro",
          "title": "נתוני אינפלציה (CPI/PPI)",
          "description": "פרסום נתוני מדד המחירים לצרכן (CPI) או מדד המחירים ליצרן (PPI) בשבועות הקרובים יקבע את הציפיות לגבי מדיניות הפד. נתונים גבוהים מהצפוי עלולים להעיד על המשך לחצי אינפלציה ולפגוע בסנטימנט השוק הכללי.",
          "impact": "שלילי (אם גבוה מהצפוי)",
          "timeframe": "שבועות"
        }
      ],
      "questions": [
        {
          "question": "כיצד ישפיע נתון התעסוקה האחרון (לדוגמה: 175,000 משרות חדשות באפריל, נמוך מהצפוי) על ציפיות השוק להורדת ריבית הפד בחודשים הקרובים, ומה משמעות הדבר עבור סקטור הטכנולוגיה ב-S&P 500?",
          "answer": "נתון תעסוקה חלש מהצפוי מצביע על התקררות מסוימת בשוק העבודה, מה שעשוי להגביר את הסבירות שהפד יתחיל להוריד ריבית מוקדם יותר. הורדת ריבית נוטה להיטיב עם סקטור הטכנולוגיה (המיוצג בכבדות ב-S&P 500) מכיוון שהיא מפחיתה את עלות ההון ומגדילה את ערך תזרימי המזומנים העתידיים, מה שמוביל לעליית מכפילים.",
          "implication": "חיובי"
        },
        {
          "question": "בהינתן ש-10 המניות הגדולות ביותר ב-SPY מהוות כ-30% ממשקל המדד, וכי חלקן נסחרות במכפילי רווח גבוהים (לדוגמה: NVDA P/E מעל 70), האם המדד חשוף מדי לתיקון בסקטור הטכנולוגיה, ומה המשמעות לפיזור הסיכון למשקיע ב-SPY?",
          "answer": "הריכוזיות הגבוהה של SPY במספר מניות טכנולוגיה גדולות אכן חושפת את הקרן לסיכון מוגבר במקרה של תיקון חד בסקטור זה. למרות שה-S&P 500 מציע פיזור רחב יותר מקרנות סקטור ספציפיות, משקיע ב-SPY למעשה מקבל חשיפה משמעותית למניות הצמיחה הגדולות, מה שמצריך בחינה של חשיפת התיק הכוללת.",
          "implication": "שלילי"
        },
        {
          "question": "בהשוואה לממוצע מחזור המסחר היומי של SPY העומד על כ-100 מיליון יחידות, האם עלייה של 15% במחזור המסחר היום, בעוד שהמדד יורד ב-0.72% ומדד ה-VIX עולה ב-5%, מעידה על מימוש רווחים רחב או על התחלה של מגמת ירידה חזקה?",
          "answer": "עלייה משמעותית במחזור המסחר בזמן ירידת מחיר המלווה בעלייה ב-VIX, מצביעה לרוב על לחץ מכירה מוגבר ומימוש רווחים רחב מצד המוסדיים. זה יכול להיות סימן להתחלה של תיקון עמוק יותר, במיוחד אם הוא מתרחש לאחר תקופה של עליות חדות וקרוב לשיאים חדשים, ומעיד על כניסת כסף גדול לכיוון המכירה.",
          "implication": "שלילי"
        }
      ],
      "price": 733.99,
      "change_pct": -0.72,
      "analyst_ratings": {
        "strongBuy": 0,
        "buy": 0,
        "hold": 0,
        "sell": 0,
        "strongSell": 0
      }
    },
    {
      "ticker": "MU",
      "company_name": "Micron Technology, Inc.",
      "sector": "טכנולוגיה",
      "signal": "תיקון טכני, פוטנציאל ריבאונד",
      "direction": "neutral",
      "confidence": 65,
      "earnings_insight": "מיקרון דיווחה לאחרונה על תוצאות חזקות לרבעון השלישי של שנת הכספים 2024, תוך עקיפת תחזיות ההכנסות והרווח למניה. ההנהלה סיפקה תחזית אופטימית לרבעון הרביעי, המונעת מביקוש חזק לזיכרון ברוחב פס גבוה (HBM) ומוצרים הקשורים לבינה מלאכותית. ההפתעה הייתה בעוצמת התמחור וההתאוששות בביקוש בשוק הזיכרון, מה שסימן סיום למחזור תיקון המלאי. זה שינה באופן משמעותי את התוכנית העסקית למינוף הזדמנויות ה-AI.",
      "bottom_line": "אזור איסוף (Entry Zone): 745.00-750.00 | יעד נזילות ראשון (Take Profit): 795.00 | נקודת ביטול תזה (Hard Stop Loss): 732.00 | יחס סיכוי/סיכון מספרי: 3.06:1",
      "catalysts": [
        {
          "type": "technical",
          "title": "תיקון טכני ובדיקת תמיכה",
          "description": "לאחר עלייה חדה, המניה יורדת ב-5.3% היום, מה שמהווה תיקון טכני ובדיקה של רמות תמיכה קריטיות סביב אזור ה-VWAP. תגובת הקונים באזור זה תקבע את המשך המגמה לטווח הקצר.",
          "impact": "לא ברור",
          "timeframe": "מיידי"
        },
        {
          "type": "business",
          "title": "המשך ביקוש חזק ל-HBM",
          "description": "הביקוש הגובר לזיכרון ברוחב פס גבוה (HBM) מצד חברות AI ממשיך לתמוך בצמיחה של מיקרון, כפי שהודגם בדוחות האחרונים. זהו מנוע צמיחה מרכזי לטווח הבינוני, המגובה בהשקעות כבדות בתשתיות AI.",
          "impact": "חיובי",
          "timeframe": "ימים/שבועות"
        },
        {
          "type": "macro",
          "title": "סנטימנט מאקרו וריביות",
          "description": "התנודתיות בשוק הרחב, במיוחד סביב ציפיות לריביות והאינפלציה, משפיעה על מניות צמיחה וטכנולוגיה כמו מיקרון. נתונים מאקרו חיוביים או ירידה בציפיות לריביות יכולים לתמוך בעלייה במניות הטכנולוגיה.",
          "impact": "לא ברור",
          "timeframe": "ימים/שבועות"
        },
        {
          "type": "squeeze",
          "title": "פוטנציאל שורט סקוויז באזורים גבוהים",
          "description": "המניה נסחרת קרוב לשיא של 52 שבועות (818.67 דולר), וירידה מהירה יכולה ללכוד סוחרים בפוזיציות שורט. חזרה מעל רמות התנגדות קריטיות עלולה להפעיל כיסוי פוזיציות מהיר ולדחוף את המחיר כלפי מעלה בעוצמה.",
          "impact": "חיובי",
          "timeframe": "מיידי/ימים"
        }
      ],
      "questions": [
        {
          "question": "בהינתן ירידה של 5.3% במחיר מניית MU היום, כיצד הנרטיב האופטימי ברשתות החברתיות לגבי AI ושבבי זיכרון מתיישב עם תנועת המחיר בפועל המעידה על מימושי רווחים או חששות?",
          "answer": "הנרטיב החיובי ארוך הטווח סביב AI ו-HBM נשאר דומיננטי, אך תנועת המחיר היום משקפת מימושי רווחים טקטיים מצד סוחרים לטווח קצר, אולי על רקע חששות מאקרו גלובליים או לאחר עלייה חדה ומהירה מדי. ישנו ניתוק זמני בין הסנטימנט הכללי לתגובת המחיר המיידית.",
          "implication": "ניטרלי"
        },
        {
          "question": "לאחר ירידה של 5.3% היום, כיצד פרופיל מחזור המסחר הנוכחי מתייחס לממוצע 30 הימים האחרונים, והאם כסף מוסדי לוחץ על אזורי הביד (Bid) או רוכש מהאסק (Ask) סביב קו ה-VWAP?",
          "answer": "אם מחזור המסחר הנוכחי גבוה משמעותית מהממוצע ל-30 יום במהלך הירידה, זה עשוי להעיד על מימושים מוסדיים אגרסיביים. אם המחזור נמוך יחסית, ייתכן שמדובר בתיקון טכני רגיל. התנהגות המחיר סביב ה-VWAP תצביע האם הקונים מצליחים לבלום את הירידה או שהמוכרים שולטים באופן מובהק.",
          "implication": "שלילי (אם מכירה מוסדית כבדה) / ניטרלי (אם תיקון טכני)"
        },
        {
          "question": "בהתחשב במחיר הנוכחי של MU שעומד על 753.17 דולר ובשיא של 52 שבועות ב-818.67 דולר, מהן רמות המחיר הקריטיות מעל המחיר הנוכחי שבהן עלול להתרחש שורט סקוויז, שיאלץ סוחרים בפוזיציות שורט לכסות הפסדים במהירות?",
          "answer": "רמות מעל 770 דולר, ובמיוחד אזור ה-785-790 דולר, יכולות לשמש כאזורי חיסול (liquidation zones) עבור שורטיסטים שנכנסו לפוזיציות באזורים אלו או קרובים לשיא. פריצה עקבית מעל רמות אלו עשויה ליצור תנועה מהירה כלפי מעלה עקב כיסוי פוזיציות כפוי.",
          "implication": "חיובי"
        }
      ],
      "buzz_alert": "הבאז סביב מניית מיקרון מוזן בעיקר מהנרטיב החזק של הביקוש לשבבי זיכרון מתקדמים (HBM) בתחום הבינה המלאכותית. חלק ניכר מהרעש מגיע מפרשנים ואנליסטים בעלי עניין, המעוניינים לשמר את הסנטימנט החיובי. בעוד שהנתונים על גידול בביקוש ל-HBM הם עובדתיים, יש לבחון בזהירות את ההתלהבות הכללית שעלולה להוביל למניפולציות של מחירי יעד. ההשפעה על הלך הרוח היא של אופטימיות יתר, אך היא גם הופכת את המניה לרגישה למימושי רווחים.",
      "sources": [
        "https://finance.yahoo.com/quote/MU/",
        "https://seekingalpha.com/symbol/MU",
        "https://finviz.com/quote.ashx?t=MU",
        "https://www.sec.gov/cgi-bin/browse-edgar?action=getcompany&CIK=0000723138&type=10-Q",
        "https://openinsider.com/screener?s=MU"
      ],
      "analysis_type": "short",
      "market": "US",
      "price": 753.17,
      "change_pct": -5.3,
      "price_target": {
        "mean": 573.9048,
        "low": 249.0,
        "high": 1000.0,
        "num_analysts": 42
      }
    },
    {
      "ticker": "MELI",
      "company_name": "מרקדו ליברה",
      "sector": "צריכה מחזורית",
      "signal": "תנועה רוחבית, מחכה לקטליזטור",
      "direction": "neutral",
      "confidence": 60,
      "earnings_insight": "בדוח הרבעוני האחרון (Q1 2024), מרקדו ליברה הציגה צמיחה חזקה בהכנסות של 36% ב-YoY, עם גידול מרשים ב-GMV (Gross Merchandise Volume) וב-TPV (Total Payment Volume). ההנהלה הדגישה את ההתרחבות בשירותי הפינטק (Mercado Pago) והשקת מוצרים חדשים כמו השקעות בקרנות נאמנות. למרות זאת, החברה רשמה FCF שלילי של 4.1 מיליארד דולר, מה שהפתיע לרעה חלק מהמשקיעים ומעלה שאלות לגבי ניהול ההון. השינוי המשמעותי הוא ההתמקדות בהרחבת האקוסיסטם הפיננסי מעבר למסחר אלקטרוני, אך עם עלויות גבוהות יותר לטווח הקצר.",
      "bottom_line": "יש לנטר את רמת 1530 דולר כתמיכה קריטית, עם יעד נזילות ראשון סביב 1580 דולר ונקודת ביטול תזה חדה ב-1520 דולר, המגלמת יחס סיכוי/סיכון של 3:1.",
      "catalysts": [
        {
          "type": "macro",
          "title": "יציבות כלכלית באמריקה הלטינית",
          "description": "היציבות הכלכלית והפוליטית במדינות מפתח כמו ברזיל ומקסיקו היא קטליזטור מרכזי. כל שיפור באינדיקטורים מאקרו-כלכליים (אינפלציה, ריבית) או חדשות חיוביות על רפורמות יכולות להגביר את אמון הצרכנים ולהניע את מניית MELI.",
          "impact": "חיובי",
          "timeframe": "שבועות/חודשים"
        },
        {
          "type": "business",
          "title": "התרחבות שירותי פינטק",
          "description": "המשך ההתרחבות של Mercado Pago והשקת שירותים פיננסיים חדשים (כמו הלוואות או השקעות) שיזכו לאימוץ נרחב, יכולים להגדיל את בסיס המשתמשים ואת ההכנסות מכל משתמש, כפי שקרה עם Mercado Credito.",
          "impact": "חיובי",
          "timeframe": "שבועות/חודשים"
        },
        {
          "type": "technical",
          "title": "בלימת ירידות באזור ה-52w_low",
          "description": "המחיר הנוכחי של 1553.98 דולר קרוב לרמת ה-52w_low של 1536.71 דולר. בלימה חזקה באזור זה והימנעות משבירה מטה יכולה לאותת על כניסת קונים ארוכי טווח ועל תחתית קצרת טווח, מה שיכול להוביל לריבאונד.",
          "impact": "חיובי",
          "timeframe": "מיידי/ימים"
        }
      ],
      "questions": [
        {
          "question": "בהינתן נתון ה-Free Cash Flow השלילי של 4.1 מיליארד דולר, כיצד MELI מתכננת לממן את הצמיחה העתידית שלה ולהגיע לרווחיות תפעולית גבוהה יותר?",
          "answer": "ה-FCF השלילי מעיד על השקעות משמעותיות בתשתית ובהרחבת פעילות. החברה תצטרך להראות שיפור ברווחיות התפעולית ובניהול ההון כדי להפיג את החששות. ייתכן שהיא תסתמך על גיוסי חוב או הון נוספים בטווח הקצר, או על שיפור שולי הרווח כתוצאה מיתרונות לגודל.",
          "implication": "שלילי"
        },
        {
          "question": "כיצד האינפלציה הגבוהה והריביות באמריקה הלטינית משפיעות על כוח הקנייה של הצרכנים ועל נתון ה-GMV של MELI, שהציגה צמיחה חזקה בדוח האחרון?",
          "answer": "אינפלציה וריביות גבוהות יכולות לשחוק את כוח הקנייה של הצרכנים, אך MELI הצליחה לשמור על צמיחת GMV חזקה. זה מעיד על עמידות המודל העסקי ועל מעבר צרכנים לפלטפורמות דיגיטליות. עם זאת, המשך ההידרדרות במצב הכלכלי עלול להשפיע לרעה על קצב הצמיחה העתידי.",
          "implication": "ניטרלי"
        },
        {
          "question": "בהינתן שדמי הניהול הממוצעים של קרנות סל דומות בארה\"ב עומדים על כ-0.2%, האם למרקדו ליברה יש יתרון תחרותי מספק כדי להצדיק את מחיר המניה הגבוה בהשוואה לחברות פינטק אחרות?",
          "answer": "השאלה מתייחסת ל-ETF/קרנות סל, ו-MELI היא מניה בודדת. אין לה דמי ניהול. עם זאת, ניתן להתייחס לשאלה במונחים של עלות ההזדמנות והשוואה לחברות דומות. יתרונותיה של MELI כוללים נתח שוק דומיננטי באזורים רבים באמריקה הלטינית ואקוסיסטם משולב של מסחר ופינטק. זה מצדיק פרמיה, אך התחרות גוברת ודורשת חדשנות מתמדת.",
          "implication": "ניטרלי"
        }
      ],
      "buzz_alert": "הבאז סביב MELI מתמקד בפוטנציאל הצמיחה העצום של אמריקה הלטינית, הן במסחר אלקטרוני והן בפינטק. רוב השיח מגיע מאנליסטים מוסדיים המתמקדים בנתוני צמיחה ונתחי שוק, אך גם משקיעים קמעונאיים מזהים את הפוטנציאל. אין עדויות חזקות למניפולציה או 'ספוּפינג' בולטים. ההשפעה על הלך הרוח היא של אופטימיות ארוכת טווח, אך עם חששות לגבי התנודתיות הכלכלית באזור והתחרות הגוברת. הרעש מוגבל יחסית למניות טכנולוגיה אחרות, מה שמאפשר התמקדות בנתונים מהותיים.",
      "sources": [
        "https://finance.yahoo.com/quote/MELI/",
        "https://seekingalpha.com/symbol/MELI",
        "https://www.sec.gov/cgi-bin/browse-edgar?action=getcompany&CIK=0001099158&type=10-Q",
        "https://www.reuters.com/companies/MELI.O"
      ],
      "analysis_type": "short",
      "market": "US",
      "price": 1553.98,
      "change_pct": -0.21,
      "price_target": {
        "mean": 2345.88,
        "low": 1800.0,
        "high": 3500.0,
        "num_analysts": 25
      }
    },
    {
      "ticker": "XYL",
      "company_name": "קסילם בע\"מ",
      "sector": "תעשייה",
      "signal": "בסמוך לשפל 52 שבועות",
      "direction": "neutral",
      "confidence": 60,
      "earnings_insight": "דוחות אחרונים הראו ביקוש יציב לפתרונות מים, אך גם התמודדות עם עלויות גבוהות ושיבושי שרשרת אספקה. ההנהלה הדגישה את חשיבות החדשנות והרחבת הפתרונות הדיגיטליים. למרות נתונים חיוביים מסוימים, השוק הגיב בחשש לגבי תחזיות הצמיחה והשפעת המאקרו על פרויקטים ארוכי טווח.",
      "bottom_line": "רמת 111.14$ (שפל 52 שבועות) היא נקודת מפתח קריטית. שבירה מטה תאותת על המשך חולשה, בעוד ריבאונד יצביע על תחתית זמנית.",
      "catalysts": [
        {
          "type": "technical",
          "title": "מבחן שפל 52 שבועות",
          "description": "המחיר הנוכחי (111.18$) נמצא ממש מעל שפל 52 השבועות (111.1401$). זהו קטליזטור טכני קריטי: שבירה מתחת לרמה זו תאותת על חולשה משמעותית, בעוד התבססות מעליה עשויה להוביל לריבאונד קצר טווח.",
          "impact": "לא ברור",
          "timeframe": "מיידי"
        },
        {
          "type": "liquidation",
          "title": "אזור חיסול פוזיציות",
          "description": "אם המניה תשבור מתחת ל-111.14$, יופעלו פקודות סטופ-לוס רבות, מה שיוביל לחיסול פוזיציות לונג. זה יכול להאיץ את הירידה במהירות של 3-5% תוך שעות, כיוון שאין תמיכה טכנית משמעותית מתחת לרמה זו.",
          "impact": "שלילי",
          "timeframe": "מיידי"
        },
        {
          "type": "macro",
          "title": "חששות מאקרו סביב תעשייה",
          "description": "החולשה במניה, למרות יעד מחיר אנליסטים של 150.82$, משקפת חששות כלליים בתעשייה לגבי האטה כלכלית או השפעת עליית הריבית על פרויקטי תשתית ארוכי טווח, מה שמקשה על המניה להתאושש.",
          "impact": "שלילי",
          "timeframe": "ימים"
        }
      ],
      "questions": [
        {
          "question": "בהינתן שהמניה נסחרת ב-111.18$ ורמת השפל של 52 השבועות היא 111.14$, האם יש עדויות בספר הפקודות (Level 2) ל'קירות' תמיכה משמעותיים ממש מתחת לרמה זו?",
          "answer": "קיר תמיכה חזק באזור 111$ יעיד על עניין קנייה מוסדי בניסיון למנוע שבירה. היעדר קיר כזה יחזק את הסיכון לשבירה מהירה מטה עם פוטנציאל לזינוק במורד.",
          "implication": "ניטרלי"
        },
        {
          "question": "כיצד הירידה הנוכחית של 0.73% משתלבת עם ביצועי מדד התעשייה הרחב יותר היום, והאם XYL מפגינה חולשה יחסית?",
          "answer": "אם מדד התעשייה יורד בשיעור נמוך יותר, או עולה, הרי ש-XYL מפגינה חולשה יחסית. חולשה זו יכולה להעיד על בעיות ספציפיות לחברה או על חוסר אמון של השוק בפוטנציאל ההתאוששות שלה בטווח הקצר.",
          "implication": "שלילי"
        }
      ],
      "buzz_alert": "הבאז סביב XYL כרגע נמוך יחסית, אך מתחיל להתעורר סביב השאלה האם המניה תשבור את שפל 52 השבועות. אין עדויות חזקות למניפולציה, אך הסנטימנט יכול להפוך במהירות לשלילי אם רמת התמיכה הקריטית תיפרץ. משקיעים קטנים עשויים להיכנס לפוזיציות 'קניה בירידה' אך הסיכון גבוה.",
      "sources": [
        "https://finance.yahoo.com/quote/XYL/",
        "https://seekingalpha.com/symbol/XYL",
        "https://www.sec.gov/cgi-bin/browse-edgar?action=getcompany&CIK=0001524472&type=10-Q",
        "https://finviz.com/quote.ashx?t=XYL",
        "https://www.reuters.com/companies/XYL.N"
      ],
      "analysis_type": "short",
      "market": "US",
      "price": 111.18,
      "change_pct": -0.73,
      "price_target": {
        "mean": 150.82353,
        "low": 124.0,
        "high": 186.0,
        "num_analysts": 17
      }
    }
  ]
}